prominence_delineator/__init__.py
prominence_delineator/prominence_delineator.py
prominence_delineator-0.0.10.dist-info/licenses/LICENSE
prominence_delineator-0.0.10.dist-info/METADATA
prominence_delineator-0.0.10.dist-info/WHEEL
prominence_delineator-0.0.10.dist-info/top_level.txt
prominence_delineator-0.0.10.dist-info/RECORD
