Metadata-Version: 2.4
Name: prominence-delineator
Version: 0.0.10
Summary: Physiology-Informed ECG Delineator Based on Peak Prominence
Author-email: Jonas Emrich <mail@jonasemrich.de>
Maintainer-email: Jonas Emrich <mail@jonasemrich.de>
License:                     GNU GENERAL PUBLIC LICENSE
Project-URL: Homepage, https://jonasemrich.de
Project-URL: Source Code, https://github.com/JonasEmrich/prominence-delineator
Keywords: delineation,delineator,ecg,cardiovascular,waves detection,waves,detector,prominence
Classifier: Programming Language :: Python :: 3
Classifier: License :: OSI Approved :: GNU General Public License v3 (GPLv3)
Classifier: Operating System :: OS Independent
Classifier: Intended Audience :: Science/Research
Requires-Python: >=3.8
License-File: LICENSE
Requires-Dist: numpy
Requires-Dist: scipy
Provides-Extra: rpeak
Requires-Dist: vg-beat-detectors; extra == "rpeak"
Provides-Extra: cleaning
Requires-Dist: neurokit2; extra == "cleaning"
Provides-Extra: example
Requires-Dist: matplotlib; extra == "example"
Requires-Dist: wfdb; extra == "example"
Provides-Extra: all
Requires-Dist: prominence-delineator[cleaning,example,rpeak]; extra == "all"
Dynamic: license-file
